jsonconfigparser.py
python_json_config_parser-1.0.9.dist-info/LICENSE-MIT
python_json_config_parser-1.0.9.dist-info/METADATA
python_json_config_parser-1.0.9.dist-info/WHEEL
python_json_config_parser-1.0.9.dist-info/top_level.txt
python_json_config_parser-1.0.9.dist-info/RECORD
