Metadata-Version: 2.1
Name: python-json-config-parser
Version: 1.0.9
Summary: Project created to given the possibility of create dynamics Json config files
Home-page: https://github.com/BrunoSilvaAndrade/python-json-config-parser
Author: Bruno Silva de Andrade
Author-email: brunojf.andrade@gmail.com
License: MIT
Platform: UNKNOWN
Classifier: Programming Language :: Python :: 3
Classifier: License :: OSI Approved :: MIT License
Classifier: Operating System :: OS Independent
License-File: LICENSE-MIT
Requires-Dist: schema (>=0.7.1)
